PALib/database/__init__.py
PALib/database/database.py
PALib/models/__init__.py
PALib/models/dto.py
PALib/models/models.py
PALib/repository/__init__.py
PALib/repository/base.py
PALib/service/__init__.py
PALib/service/service.py
personadresssaraivagustavo-0.1.2.dist-info/licenses/LICENSE
personadresssaraivagustavo-0.1.2.dist-info/METADATA
personadresssaraivagustavo-0.1.2.dist-info/WHEEL
personadresssaraivagustavo-0.1.2.dist-info/top_level.txt
personadresssaraivagustavo-0.1.2.dist-info/RECORD
