Metadata-Version: 2.4
Name: PERSONADRESSsaraivagustavo
Version: 0.1.2
Summary: Biblioteca para gerenciamento de pessoas e endereços, utilizando banco de dados em memória com SQLModel.
Home-page: https://github.com/saraivagustavo/PersonAdressLib
Author: Gustavo Saraiva Mariano
Author-email: gsaraivam10@gmail.com
License: MIT
Classifier: Programming Language :: Python :: 3
Classifier: License :: OSI Approved :: MIT License
Classifier: Operating System :: OS Independent
Requires-Python: >=3.8
License-File: LICENSE
Requires-Dist: sqlmodel
Requires-Dist: typing_extensions
Requires-Dist: fastapi
Provides-Extra: dev
Requires-Dist: pytest>=7.0; extra == "dev"
Dynamic: author
Dynamic: author-email
Dynamic: classifier
Dynamic: description
Dynamic: description-content-type
Dynamic: home-page
Dynamic: license
Dynamic: license-file
Dynamic: provides-extra
Dynamic: requires-dist
Dynamic: requires-python
Dynamic: summary
